Metadata-Version: 2.1
Name: PyOpenQP
Version: 1.1
Summary: Python bindings for the Open Quantum Platform (Fortran core + Python wrapper)
Author-Email: Mohsen Mazaherifar <moh.mazaheri@gmail.com>
License: GPLv3
Requires-Python: >=3.9
Requires-Dist: numpy>=1.20.0
Requires-Dist: scipy>=1.10.0
Requires-Dist: libdlfind>=0.0.3
Requires-Dist: cffi>=1.16.0
Requires-Dist: basis_set_exchange
